mlflow_nbconvert.py
mlflow_nbconvert-1.0.0.dist-info/LICENSE
mlflow_nbconvert-1.0.0.dist-info/WHEEL
mlflow_nbconvert-1.0.0.dist-info/METADATA
mlflow_nbconvert-1.0.0.dist-info/RECORD
