Metadata-Version: 2.1
Name: mlflow_nbconvert
Version: 1.0.0
Summary: mlflow-nbconvert
Home-page: UNKNOWN
License: UNKNOWN
Author: Tom Augspurger
Author-email: tom.w.augspurger@gmail.com
Classifier: License :: OSI Approved :: MIT License
